pymusicterm/__init__.py
pymusicterm/__main__.py
pymusicterm/music/__init__.py
pymusicterm/music/player.py
pymusicterm/ui/__init__.py
pymusicterm/ui/labels.py
pymusicterm/ui/menus.py
pymusicterm/ui/progressbar.py
pymusicterm/ui/widget_set.py
pymusicterm/ui/windows.py
pymusicterm/util/__init__.py
pymusicterm/util/file.py
pymusicterm/util/system.py
pymusicterm/util/time.py
tests/music/__init__.py
tests/music/test_song_file.py
tests/util/__init__.py
tests/util/test_file.py
tests/util/test_system.py
tests/util/test_time.py
pymusic_term-0.0.4.dist-info/AUTHORS
pymusic_term-0.0.4.dist-info/LICENSE
pymusic_term-0.0.4.dist-info/METADATA
pymusic_term-0.0.4.dist-info/WHEEL
pymusic_term-0.0.4.dist-info/entry_points.txt
pymusic_term-0.0.4.dist-info/top_level.txt
pymusic_term-0.0.4.dist-info/RECORD
