Metadata-Version: 2.1
Name: pymusic-term
Version: 0.0.4
Summary: A music player and spotify client for a terminal
Home-page: https://github.com/EGAMAGZ/pymusicterm
Author: Gamaliel Garcia
Author-email: 
License: MIT
Keywords: git cli cui curses command-line
Platform: UNKNOWN
Classifier: Intended Audience :: Information Technology
Classifier: Development Status :: 3 - Alpha
Classifier: Environment :: Console
Classifier: Environment :: Console :: Curses
Classifier: License :: OSI Approved :: MIT License
Classifier: Programming Language :: Python :: 3.8
Classifier: Topic :: Multimedia :: Sound/Audio :: Players
Classifier: Topic :: Multimedia :: Sound/Audio :: Players :: MP3
Requires-Python: >=3.8
Requires-Dist: mutagen (==1.45.1)
Requires-Dist: py-cui (==0.1.1)
Requires-Dist: pygame (==1.9.6)
Requires-Dist: pytaglib (==1.4.6)
Requires-Dist: windows-curses (==2.1.0)
